README.txt
setup.py
motion_2860/MPC2860.dll
motion_2860/MPC2860.h
motion_2860/MPC2860.lib
motion_2860/MPC2860CFG.txt
motion_2860/__init__.py
motion_2860/motion_2860.h
motion_2860/motion_2860.py
motion_2860/motion_2860_wrap.cxx
motion_2860.egg-info/PKG-INFO
motion_2860.egg-info/SOURCES.txt
motion_2860.egg-info/dependency_links.txt
motion_2860.egg-info/top_level.txt