Metadata-Version: 1.1
Name: motion-2860
Version: 0.3
Summary: Python module for motion 2860
Home-page: https://github.com/KD-Group/motion_2860
Author: SF Zhou WingC
Author-email: 1018957763@qq.com
License: GPL
Platform: UNKNOWN
Classifier: Development Status :: 3 - Alpha
Classifier: Intended Audience :: Developers
Classifier: License :: OSI Approved :: GNU Affero General Public License v3
Classifier: Programming Language :: Python :: 3
